LICENSE
MANIFEST.in
README.md
setup.py
django_enhanced_emails.egg-info/PKG-INFO
django_enhanced_emails.egg-info/SOURCES.txt
django_enhanced_emails.egg-info/dependency_links.txt
django_enhanced_emails.egg-info/requires.txt
django_enhanced_emails.egg-info/top_level.txt
enhanced_emails/__init__.py
enhanced_emails/admin.py
enhanced_emails/apps.py
enhanced_emails/emails.py
enhanced_emails/models.py
enhanced_emails/urls.py
enhanced_emails/views.py