Metadata-Version: 2.1
Name: django-enhanced-emails
Version: 0.0.6
Summary: Enhanced email classes for Django
Home-page: https://github.com/Theodo-UK/django-enhanced-emails
Author: Nathan Gaberel
Author-email: nathang@theodo.co.uk
License: Theodo
Keywords: class based emails django
Platform: UNKNOWN
Classifier: Development Status :: 5 - Production/Stable
Classifier: Environment :: Web Environment
Classifier: Framework :: Django
Classifier: Intended Audience :: Developers
Classifier: License :: OSI Approved :: MIT License
Classifier: Programming Language :: Python :: 3.4
Classifier: Programming Language :: Python :: 3.5
Classifier: Programming Language :: Python :: 3.6
Classifier: Programming Language :: Python :: 3.7
Classifier: Topic :: Communications :: Email
